klefki_gen/__init__.py
klefki_gen/__main__.py
klefki_gen-1.0.5.dist-info/licenses/LICENSE
klefki_gen-1.0.5.dist-info/METADATA
klefki_gen-1.0.5.dist-info/WHEEL
klefki_gen-1.0.5.dist-info/entry_points.txt
klefki_gen-1.0.5.dist-info/top_level.txt
klefki_gen-1.0.5.dist-info/RECORD
